k8s_mcp_server/__init__.py
k8s_mcp_server/__main__.py
k8s_mcp_server/cli_executor.py
k8s_mcp_server/config.py
k8s_mcp_server/errors.py
k8s_mcp_server/prompts.py
k8s_mcp_server/security.py
k8s_mcp_server/server.py
k8s_mcp_server/tools.py
orange_k8s_mcp_server-1.1.0.dist-info/licenses/LICENSE
orange_k8s_mcp_server-1.1.0.dist-info/METADATA
orange_k8s_mcp_server-1.1.0.dist-info/WHEEL
orange_k8s_mcp_server-1.1.0.dist-info/top_level.txt
orange_k8s_mcp_server-1.1.0.dist-info/RECORD
